Metadata-Version: 2.1
Name: genmobile
Version: 0.4.0
Summary: Java ROS message and service generators.
Author: Ronaldson Bellande
Maintainer: Ronaldson Bellande
Maintainer-email: ronaldsonbellande@gmail.com
License: BSD
Requires: genmsg
License-File: LICENSE
